aidea/__init__.py
aidea/main.py
aidea/tools.py
aidea-1.1.0.dist-info/LICENSE
aidea-1.1.0.dist-info/METADATA
aidea-1.1.0.dist-info/WHEEL
aidea-1.1.0.dist-info/entry_points.txt
aidea-1.1.0.dist-info/top_level.txt
aidea-1.1.0.dist-info/RECORD
