Metadata-Version: 2.1
Name: aidea
Version: 1.1.0
Summary: AIdea API
Home-page: UNKNOWN
Author: AIdea
Author-email: admin.AIdea@itri.org.tw
License: UNKNOWN
Platform: UNKNOWN
Classifier: Programming Language :: Python :: 3
Classifier: License :: OSI Approved :: Apache Software License
Requires-Python: >=3.6
License-File: LICENSE
Requires-Dist: requests
Requires-Dist: texttable
Requires-Dist: tqdm
Requires-Dist: icecream
Requires-Dist: requests-toolbelt
